py_outfit-1.0.0.dist-info/METADATA
py_outfit-1.0.0.dist-info/WHEEL
py_outfit-1.0.0.dist-info/licenses/LICENSE
py_outfit/__init__.py
py_outfit/__init__.pyi
py_outfit/iod_gauss.pyi
py_outfit/iod_params.pyi
py_outfit/observations.pyi
py_outfit/observer.pyi
py_outfit/orbit_type/__init__.pyi
py_outfit/orbit_type/cometary.pyi
py_outfit/orbit_type/equinoctial.pyi
py_outfit/orbit_type/keplerian.pyi
py_outfit/pandas_pyoutfit.py
py_outfit/py.typed
py_outfit/py_outfit.cpython-311-x86_64-linux-gnu.so
py_outfit/py_outfit.pyi
py_outfit/trajectories.pyi
py_outfit-1.0.0.dist-info/RECORD
