Metadata-Version: 2.4
Name: py-outfit
Version: 1.0.0
Classifier: Development Status :: 5 - Production/Stable
Classifier: Intended Audience :: Science/Research
Classifier: Intended Audience :: Developers
Classifier: License :: CeCILL-C Free Software License Agreement (CECILL-C)
Classifier: Programming Language :: Python :: 3
Classifier: Programming Language :: Python :: 3 :: Only
Classifier: Programming Language :: Python :: 3.12
Classifier: Programming Language :: Rust
Classifier: Natural Language :: English
Classifier: Operating System :: POSIX :: Linux
Classifier: Topic :: Scientific/Engineering :: Astronomy
Classifier: Topic :: Scientific/Engineering :: Physics
Classifier: Topic :: Scientific/Engineering :: Information Analysis
Classifier: Topic :: Software Development :: Libraries :: Python Modules
Classifier: Typing :: Typed
Requires-Dist: maturin>=1.9.4
Requires-Dist: pip>=25.2
Requires-Dist: numpy>=2.3.3
Requires-Dist: pandas>=2.3.2
Requires-Dist: astropy>=7.1.0
Requires-Dist: pyarrow>=21.0.0
License-File: LICENSE
License-File: LICENSE
Summary: Python bindings for Outfit (Rust) — Gauss IOD, ephemerides, etc.
Keywords: astronomy,orbit-determination,rust,pyo3,maturin
Author-email: FusRoman <roman.le-montagner@ijclab.in2p3.fr>
Requires-Python: >=3.12
